daocube/__init__.py
daocube/daocube.py
daocube/daocube_backend.py
daocube/daophot_pipeline.py
daofun/__init__.py
daofun/daofun.py
daofun/daofun_backend.py
daofun/daofun_gui_inspect.py
daofun/daofun_gui_selection.py
daofun/daophot_opt.py
daofun/daophot_wraps.py
daofun/fits_handler.py
daofun/misc_tools.py
specfun/__init__.py
specfun/fits2df.py
specfun/spec_crop.py
specfun/spec_maskednorm_poly.py
specfun/spec_nan_corr.py
specfun/spec_norm_poly.py
specfun/spec_rv.py
specfun/spec_rv_corr.py
specfun/spec_rv_err.py
specfun/spec_snr.py
specfun/spec_snr_pp.py
specfun/spec_telluric_corr.py
specfun/spec_wavelength_sync.py
specfun/specfun.py
specfun/specfun_backend.py
specfun/specfun_command.py
daofun-0.2.0.dist-info/LICENSE.txt
daofun-0.2.0.dist-info/METADATA
daofun-0.2.0.dist-info/WHEEL
daofun-0.2.0.dist-info/entry_points.txt
daofun-0.2.0.dist-info/top_level.txt
daofun-0.2.0.dist-info/RECORD
