Metadata-Version: 2.1
Name: daofun
Version: 0.2.0
Summary: DAOFUN is an interactive adaptation of the DAOPHOT 
Home-page: https://github.com/ciquezada/daofun
Author: Carlos Quezada
License: MIT
Keywords: daophot,astronomical,python
License-File: LICENSE.txt
Requires-Dist: numpy (==1.21.6)
Requires-Dist: pandas (==1.3.5)
Requires-Dist: matplotlib (==3.5.3)
Requires-Dist: astropy (==4.3.1)
Requires-Dist: aplpy (==2.1.0)
Requires-Dist: IPython (==7.34.0)
Requires-Dist: PySimpleGUI (==4.60.5)
Requires-Dist: spectral-cube
Requires-Dist: tqdm (==4.66.1)
Requires-Dist: specutils (==1.8.1)
